setup.py
qtl_models/__init__.py
qtl_models/enums.py
qtl_models.egg-info/PKG-INFO
qtl_models.egg-info/SOURCES.txt
qtl_models.egg-info/dependency_links.txt
qtl_models.egg-info/requires.txt
qtl_models.egg-info/top_level.txt