Metadata-Version: 1.0
Name: qtl-models
Version: 0.0.1
Summary: Quantalon Toolkit Models
Home-page: UNKNOWN
Author: UNKNOWN
Author-email: UNKNOWN
License: UNKNOWN
Platform: UNKNOWN
